pypdm/__init__.py
pypdm/_pdm.py
pypdm/builder.py
pypdm/assist/__init__.py
pypdm/assist/cfg.py
pypdm/assist/num.py
pypdm/dao/__init__.py
pypdm/dao/_base.py
pypdm/dbc/__init__.py
pypdm/dbc/_mysql.py
pypdm/dbc/_sqlite.py
pypdm_db-1.1.6.dist-info/LICENSE.txt
pypdm_db-1.1.6.dist-info/METADATA
pypdm_db-1.1.6.dist-info/WHEEL
pypdm_db-1.1.6.dist-info/entry_points.txt
pypdm_db-1.1.6.dist-info/top_level.txt
pypdm_db-1.1.6.dist-info/RECORD
